{
	"id": "918f83aa-310f-4e28-9e29-7a15a627cba1",
	"name": "SPRING_BOOT",
	"values": [
		{
			"key": "host",
			"value": "http://localhost:8080",
			"enabled": true
		},
		{
			"key": "user",
			"value": "leandro",
			"enabled": true
		},
		{
			"key": "password",
			"value": "admin123",
			"enabled": true
		},
		{
			"key": "bearer_token",
			"value": "",
			"enabled": true
		}
	],
	"_postman_variable_scope": "environment",
	"_postman_exported_at": "2022-05-10T20:29:25.902Z",
	"_postman_exported_using": "Postman/8.12.4"
}